{
  "main": {
    "id": "6ffc9ab4b7988661",
    "type": "split",
    "children": [
      {
        "id": "7adcc234429b284b",
        "type": "tabs",
        "children": [
          {
            "id": "534b2c51e591ec79",
            "type": "leaf",
            "state": {
              "type": "markdown",
              "state": {
                "file": "Lezioni/Priorità_Studio.md",
                "mode": "preview",
                "source": false
              },
              "icon": "lucide-file",
              "title": "Priorità_Studio"
            }
          }
        ]
      }
    ],
    "direction": "vertical"
  },
  "left": {
    "id": "58db054b487e2b13",
    "type": "split",
    "children": [
      {
        "id": "d4185ddf721af2ca",
        "type": "tabs",
        "children": [
          {
            "id": "141494977917d3c6",
            "type": "leaf",
            "state": {
              "type": "file-explorer",
              "state": {
                "sortOrder": "alphabetical",
                "autoReveal": false
              },
              "icon": "lucide-folder-closed",
              "title": "Esplora risorse"
            }
          },
          {
            "id": "75302055d8d5cbfb",
            "type": "leaf",
            "state": {
              "type": "search",
              "state": {
                "query": "fasi sensibili",
                "matchingCase": false,
                "explainSearch": false,
                "collapseAll": false,
                "extraContext": false,
                "sortOrder": "alphabetical"
              },
              "icon": "lucide-search",
              "title": "Ricerca"
            }
          },
          {
            "id": "51a25ee396fcd748",
            "type": "leaf",
            "state": {
              "type": "bookmarks",
              "state": {},
              "icon": "lucide-bookmark",
              "title": "Bookmarks"
            }
          }
        ]
      }
    ],
    "direction": "horizontal",
    "width": 300,
    "collapsed": true
  },
  "right": {
    "id": "d4878e58b968b8ed",
    "type": "split",
    "children": [
      {
        "id": "18d97362d795286e",
        "type": "tabs",
        "children": [
          {
            "id": "664d1b16513f0e1d",
            "type": "leaf",
            "state": {
              "type": "backlink",
              "state": {
                "file": "3. Il Corpo Umano (Parte 2).md",
                "collapseAll": false,
                "extraContext": false,
                "sortOrder": "alphabetical",
                "showSearch": false,
                "searchQuery": "",
                "backlinkCollapsed": false,
                "unlinkedCollapsed": true
              },
              "icon": "links-coming-in",
              "title": "Backlinks for 3. Il Corpo Umano (Parte 2)"
            }
          },
          {
            "id": "bf96738d3c75855c",
            "type": "leaf",
            "state": {
              "type": "outgoing-link",
              "state": {
                "file": "3. Il Corpo Umano (Parte 2).md",
                "linksCollapsed": false,
                "unlinkedCollapsed": true
              },
              "icon": "links-going-out",
              "title": "Outgoing links from 3. Il Corpo Umano (Parte 2)"
            }
          },
          {
            "id": "dc7b5106536f3770",
            "type": "leaf",
            "state": {
              "type": "tag",
              "state": {
                "sortOrder": "frequency",
                "useHierarchy": true,
                "showSearch": false,
                "searchQuery": ""
              },
              "icon": "lucide-tags",
              "title": "Tags"
            }
          },
          {
            "id": "b0c3ff8f12b107e7",
            "type": "leaf",
            "state": {
              "type": "all-properties",
              "state": {
                "sortOrder": "frequency",
                "showSearch": false,
                "searchQuery": ""
              },
              "icon": "lucide-archive",
              "title": "All properties"
            }
          },
          {
            "id": "3ef3a15152466b84",
            "type": "leaf",
            "state": {
              "type": "outline",
              "state": {
                "file": "3. Il Corpo Umano (Parte 2).md",
                "followCursor": false,
                "showSearch": false,
                "searchQuery": ""
              },
              "icon": "lucide-list",
              "title": "Outline of 3. Il Corpo Umano (Parte 2)"
            }
          }
        ]
      }
    ],
    "direction": "horizontal",
    "width": 300,
    "collapsed": true
  },
  "left-ribbon": {
    "hiddenItems": {
      "switcher:Apri selezione rapida": false,
      "graph:Apri vista grafo": false,
      "canvas:Crea nuova lavagna": false,
      "daily-notes:Apri nota del giorno": false,
      "templates:Inserisci modello": false,
      "command-palette:Apri riquadro comandi": false,
      "bases:Crea nuova Base": false
    }
  },
  "active": "534b2c51e591ec79",
  "lastOpenFiles": [
    "Lezioni/13.Tecnica e didattica delle quattro nuotate regolamentari.md",
    "Lezioni/Priorità_Studio.md",
    "Lezioni/11.Ambientamento e acquaticita.md",
    "Lezioni/12.Galleggiamenti spostamenti posture propulsioni.md",
    "Lezioni/Indice_Analitico.md",
    "Lezioni/18.Il Nuoto per Salvamento in Corsia.md",
    "Lezioni/1. Aspetti Amministrativi.md",
    "Lezioni/14.La Pallanuoto in Corsia parte I.md",
    "Lezioni/4.Teoria del movimento.md",
    "Corso istruttori FIN 2025 new.md",
    "Corso istruttori FIN 2025.md",
    "Corso istruttori FIN 2025.pdf",
    "combined.md",
    "Corso istruttori FIN 2025.synctex(busy)",
    "pdflatex52978.fls",
    "Corso istruttori FIN 2025.fdb_latexmk",
    "Corso istruttori FIN 2025.aux",
    "Corso istruttori FIN 2025.log",
    "Corso istruttori FIN 2025.fls",
    "pdflatex52895.fls",
    "pdflatex52790.fls",
    "pdflatex52647.fls",
    "16.Il Nuoto Artistico in Corsia parte I.md",
    "4.Teoria del movimento.md",
    "Corso_completo.md",
    "Pasted image 20260309113532.png",
    "Pics/Pasted image 20260309105700.png",
    "1. Aspetti Amministrativi.md",
    "3.Il Corpo Umano parte II.md",
    "2.Il Corpo Umano parte I.md",
    "1. Aspetti amministrativi.md",
    "4. Teoria del Movimento.md",
    "3. Il Corpo Umano (Parte 2).md",
    "2. Il Corpo Umano (Parte 1).md",
    "6.Area psicopedagogica 2.md",
    "28.Le Scuole Nuoto Federali.md",
    "27.L'Avviamento all'Attività Sportiva.md",
    "26.L'Organizzazione del Centro Natatorio.md",
    "Pics/Pasted image 20260309105909.png",
    "Pics/Pasted image 20260309105803.png",
    "Pics/Pasted image 20260309105712.png"
  ]
}